flask_rsa/__init__.py
flask_rsa/flask_rsa.py
Flask_RSA-0.2.2.dist-info/LICENSE
Flask_RSA-0.2.2.dist-info/METADATA
Flask_RSA-0.2.2.dist-info/WHEEL
Flask_RSA-0.2.2.dist-info/top_level.txt
Flask_RSA-0.2.2.dist-info/RECORD
