Metadata-Version: 2.1
Name: Flask-RSA
Version: 0.2.2
Summary: This Flask extension provides server-side implementation of RSA-based request signature validation.
Home-page: https://github.com/mwalkowski/flask-rsa
Author: mwalkowski
Author-email: Michal Walkowski <michal.walkowski@pwr.edu.pl>
License: MIT License
Project-URL: Homepage, https://github.com/mwalkowski/flask-rsa
Project-URL: Issues, https://github.com/mwalkowski/flask-rsa/issues
Keywords: Flask,RSA,REST,Views
Classifier: Programming Language :: Python :: 3
Classifier: License :: OSI Approved :: MIT License
Classifier: Operating System :: OS Independent
Requires-Python: >=3.8
License-File: LICENSE
Requires-Dist: flask
Requires-Dist: requests
Requires-Dist: pycryptodome ==3.19.1
